[   {"id":1,"name":"Телефоны","type":"Автомобили"},
    {"id":2,"name":"Компьютеры","type":"Автомобили"},
    {"id":3,"name":"Фото / видео","type":"Автомобили"},
    {"id":4,"name":"Тв / видеотехника","type":"Автомобили"},
    {"id":5,"name":"Аудиотехника","type":"Автомобили"},
    {"id":6,"name":"Игры и игровые приставки","type":"Автомобили"},
    {"id":7,"name":"Техника для дома","type":"Автомобили"},
    {"id":8,"name":"Техника для кухни","type":"Автомобили"},
    {"id":9,"name":"Климатическое оборудование","type":"Автомобили"},
    {"id":10,"name":"Индивидуальный уход","type":"Автомобили"},
    {"id":11,"name":"Аксессуары и комплектующие","type":"Автомобили"},
    {"id":12,"name":"Прочая электроника","type":"Автомобили"},
    {"id":13,"name":"Телефоны","type":"Автомобили"},
    {"id":14,"name":"Компьютеры","type":"Автомобили"},
    {"id":15,"name":"Фото / видео","type":"Автомобили"},
    {"id":16,"name":"Телефоны","type":"Автомобили"},
    {"id":17,"name":"Компьютеры","type":"Автомобили"},
    {"id":18,"name":"Фото / видео","type":"Автомобили"},
    {"id":19,"name":"Тв / видеотехника","type":"Автомобили"},
    {"id":20,"name":"Аудиотехника","type":"Автомобили"},
    {"id":21,"name":"Тв / видеотехника","type":"Недвижимость"},
    {"id":22,"name":"Аудиотехника","type":"Недвижимость"},
    {"id":23,"name":"Игры и игровые приставки","type":"Недвижимость"},
    {"id":24,"name":"Техника для дома","type":"Недвижимость"},
    {"id":25,"name":"Техника для кухни","type":"Недвижимость"},
    {"id":26,"name":"Климатическое оборудование","type":"Недвижимость"},
    {"id":27,"name":"Индивидуальный уход","type":"Недвижимость"},
    {"id":28,"name":"Аксессуары и комплектующие","type":"Недвижимость"},
    {"id":29,"name":"Прочая электроника","type":"Недвижимость"},
    {"id":30,"name":"Телефоны","type":"Недвижимость"},
    {"id":31,"name":"Компьютеры","type":"Недвижимость"},
    {"id":32,"name":"Фото / видео","type":"Недвижимость"},
    {"id":33,"name":"Телефоны","type":"Недвижимость"},
    {"id":34,"name":"Компьютеры","type":"Недвижимость"},
    {"id":35,"name":"Фото / видео","type":"Недвижимость"},
    {"id":36,"name":"Тв / видеотехника","type":"Недвижимость"},
    {"id":37,"name":"Аудиотехника","type":"Недвижимость"},
    {"id":38,"name":"Индивидуальный уход","type":"Электроника"},
    {"id":39,"name":"Аксессуары и комплектующие","type":"Электроника"},
    {"id":40,"name":"Прочая электроника","type":"Электроника"},
    {"id":41,"name":"Телефоны","type":"Электроника"},
    {"id":42,"name":"Компьютеры","type":"Электроника"},
    {"id":43,"name":"Фото / видео","type":"Электроника"},
    {"id":44,"name":"Телефоны","type":"Электроника"},
    {"id":45,"name":"Компьютеры","type":"Электроника"},
    {"id":46,"name":"Фото / видео","type":"Электроника"},
    {"id":47,"name":"Тв / видеотехника","type":"Электроника"},
    {"id":48,"name":"Аудиотехника","type":"Электроника"},
    {"id":49,"name":"Тв / видеотехника","type":"Электроника"},
    {"id":50,"name":"Аудиотехника","type":"Работа"},
    {"id":60,"name":"Игры и игровые приставки","type":"Работа"},
    {"id":61,"name":"Техника для дома","type":"Работа"},
    {"id":62,"name":"Техника для кухни","type":"Работа"},
    {"id":63,"name":"Климатическое оборудование","type":"Работа"},
    {"id":64,"name":"Индивидуальный уход","type":"Работа"},
    {"id":65,"name":"Аксессуары и комплектующие","type":"Личные вещи"},
    {"id":66,"name":"Прочая электроника","type":"Личные вещи"},
    {"id":67,"name":"Телефоны","type":"Личные вещи"},
    {"id":68,"name":"Компьютеры","type":"Личные вещи"},
    {"id":69,"name":"Фото / видео","type":"Личные вещи"},
    {"id":70,"name":"Телефоны","type":"Личные вещи"},
    {"id":71,"name":"Компьютеры","type":"Личные вещи"},
    {"id":72,"name":"Фото / видео","type":"Личные вещи"},
    {"id":73,"name":"Тв / видеотехника","type":"Личные вещи"},
    {"id":74,"name":"Аудиотехника","type":"Личные вещи"},
    {"id":75,"name":"Прочая электроника","type":"Дом и Сад"},
    {"id":76,"name":"Телефоны","type":"Дом и Сад"},
    {"id":77,"name":"Компьютеры","type":"Дом и Сад"},
    {"id":78,"name":"Фото / видео","type":"Дом и Сад"},
    {"id":79,"name":"Телефоны","type":"Дом и Сад"},
    {"id":80,"name":"Компьютеры","type":"Дом и Сад"},
    {"id":81,"name":"Фото / видео","type":"Дом и Сад"},
    {"id":82,"name":"Тв / видеотехника","type":"Дом и Сад"},
    {"id":83,"name":"Аудиотехника","type":"Стройка и ремонт"},
    {"id":84,"name":"Тв / видеотехника","type":"Стройка и ремонт"},
    {"id":85,"name":"Аудиотехника","type":"Хобби и Спорт"},
    {"id":86,"name":"Игры и игровые приставки","type":"Хобби и Спорт"},
    {"id":87,"name":"Техника для дома","type":"Хобби и Спорт"},
    {"id":88,"name":"Техника для кухни","type":"Работа"},
    {"id":89,"name":"Климатическое оборудование","type":"Работа"},
    {"id":90,"name":"Индивидуальный уход","type":"Работа"},
    {"id":91,"name":"Аксессуары и комплектующие","type":"Бизнес и услуги"},
    {"id":92,"name":"Прочая электроника","type":"Бизнес и услуги"},
    {"id":93,"name":"Телефоны","type":"Бизнес и услуги"},
    {"id":94,"name":"Компьютеры","type":"Бизнес и услуги"},
    {"id":95,"name":"Фото / видео","type":"Бизнес и услуги"},
    {"id":96,"name":"Телефоны","type":"Бизнес и услуги"},
    {"id":97,"name":"Компьютеры","type":"Бизнес и услуги"},
    {"id":98,"name":"Фото / видео","type":"Бизнес и услуги"},
    {"id":99,"name":"Тв / видеотехника","type":"Бизнес и услуги"},
    {"id":100,"name":"Аудиотехника","type":"Бизнес и услуги"}
]